koolsla/__init__.py
koolsla/color_print.py
koolsla/data.py
koolsla/recommender.py
koolsla/tfidf.py
koolsla/dataset/dish.csv
koolsla-0.3.0.dist-info/COPYING
koolsla-0.3.0.dist-info/LICENSE
koolsla-0.3.0.dist-info/METADATA
koolsla-0.3.0.dist-info/NOTICE
koolsla-0.3.0.dist-info/WHEEL
koolsla-0.3.0.dist-info/top_level.txt
koolsla-0.3.0.dist-info/RECORD
