Metadata-Version: 2.1
Name: koolsla
Version: 0.3.0
Summary: Food recommendation tool with Machine learning
Home-page: https://github.com/abdullahselek/koolsla
Author: Abdullah Selek
Author-email: abdullahselek@gmail.com
Maintainer: Abdullah Selek
Maintainer-email: abdullahselek@gmail.com
License: MIT License
Download-URL: https://pypi.org/pypi/koolsla/
Keywords: machine learning,food suggestion,tf-idf,cosine similarity
Platform: Any
Classifier: Intended Audience :: Developers
Classifier: Intended Audience :: Science/Research
Classifier: License :: OSI Approved :: MIT License
Classifier: Operating System :: OS Independent
Classifier: Topic :: Software Development
Classifier: Topic :: Scientific/Engineering
Classifier: Programming Language :: Python
Classifier: Programming Language :: Python :: 3.5
Classifier: Programming Language :: Python :: 3.6
Classifier: Programming Language :: Python :: 3.7
Classifier: Programming Language :: Python :: 3.8
Requires-Python: >=3.5
Requires-Dist: termcolor
Requires-Dist: pandas
Requires-Dist: click
Requires-Dist: colorama
Requires-Dist: scikit-learn
Requires-Dist: scipy
